aliyun_swarm_sdk/__init__.py
aliyun_swarm_sdk/aliyun_swarm_sdk.py
aliyun_swarm_sdk-4.2.dist-info/METADATA
aliyun_swarm_sdk-4.2.dist-info/WHEEL
aliyun_swarm_sdk-4.2.dist-info/top_level.txt
aliyun_swarm_sdk-4.2.dist-info/RECORD
