Metadata-Version: 2.1
Name: aliyun-swarm-sdk
Version: 4.2
Summary: 阿里云 swarm SDK
Home-page: UNKNOWN
Author: eagle
Author-email: 1032231418@qq.com
License: Apache License Version 2.0
Project-URL: Source, https://github.com/1032231418/aliyun_swarm_sdk
Platform: UNKNOWN
Classifier: Programming Language :: Python :: 3
Classifier: License :: OSI Approved :: MIT License
Classifier: Operating System :: OS Independent
Requires-Python: >=3.6
